MANIFEST.in
setup.py
ansible_role_installer/__init__.py
ansible_role_installer/__init__.pyc
ansible_role_installer/ari.py
ansible_role_installer/ari.pyc
ansible_role_installer/runner.py
ansible_role_installer.egg-info/PKG-INFO
ansible_role_installer.egg-info/SOURCES.txt
ansible_role_installer.egg-info/dependency_links.txt
ansible_role_installer.egg-info/entry_points.txt
ansible_role_installer.egg-info/requires.txt
ansible_role_installer.egg-info/top_level.txt