Metadata-Version: 1.0
Name: ansible-role-installer
Version: 0.2
Summary: Install Ansible roles from Git repositories
Home-page: http://github.com/futurice/ansible_role_installer
Author: Jussi Vaihia
Author-email: jussi.vaihia@futurice.com
License: BSD
Keywords: ansible role installer
Platform: UNKNOWN
